pangolier/__init__.py
pangolier/bin_op.py
pangolier/common.py
pangolier/filters.py
pangolier/functions.py
pangolier/label.py
pangolier/metrics.py
pangolier/prefixes.py
pangolier/py.typed
pangolier-0.4.0.dist-info/METADATA
pangolier-0.4.0.dist-info/WHEEL
pangolier-0.4.0.dist-info/top_level.txt
pangolier-0.4.0.dist-info/RECORD
