Metadata-Version: 2.4
Name: pangolier
Version: 0.4.0
Summary: build PromQL by Python code
Author: Elephant Liu
License-Expression: MIT
Project-URL: Documentation, https://pangolier.readthedocs.io
Project-URL: Source, https://github.com/xospc/pangolier
Classifier: Programming Language :: Python :: 3
Requires-Python: >=3.10
